{"cameraMode":{"drawMode":0,"name":"Shaded","section":"Shading Mode"},"sceneLighting":false,"audioPlay":false,"sceneViewState":{"m_AlwaysRefresh":false,"showFog":true,"showSkybox":false,"showFlares":true,"showImageEffects":true,"showParticleSystems":true,"showVisualEffectGraphs":true,"m_FxEnabled":true},"in2DMode":false,"pivot":{"x":-0.09037084132432938,"y":-0.3721509277820587,"z":0.4734973907470703},"rotation":{"x":0.3650042414665222,"y":0.06833893805742264,"z":-0.026876116171479226,"w":0.9281073212623596},"size":0.8934546709060669,"orthographic":false}